{"assets/images/angry.png":["assets/images/angry.png"],"assets/images/cool.png":["assets/images/cool.png"],"assets/images/crying.png":["assets/images/crying.png"],"assets/images/emoji-2.png":["assets/images/emoji-2.png"],"assets/images/emoji-3.png":["assets/images/emoji-3.png"],"assets/images/emoji-4.png":["assets/images/emoji-4.png"],"assets/images/emoji.png":["assets/images/emoji.png"],"assets/images/ez.gif":["assets/images/ez.gif"],"assets/images/party.png":["assets/images/party.png"],"assets/images/poop.png":["assets/images/poop.png"],"assets/images/shocked.png":["assets/images/shocked.png"],"assets/images/thinking.png":["assets/images/thinking.png"],"packages/cupertino_icons/assets/CupertinoIcons.ttf":["packages/cupertino_icons/assets/CupertinoIcons.ttf"]}